smc_movement_models/__init__.py
smc_movement_models/models.py
smc_movement_models/models_SMC2.py
smc_movement_models/plots.py
smc_movement_models/process_data.py
smc_movement_models-1.0.0.dist-info/LICENSE
smc_movement_models-1.0.0.dist-info/METADATA
smc_movement_models-1.0.0.dist-info/WHEEL
smc_movement_models-1.0.0.dist-info/RECORD
