Metadata-Version: 2.1
Name: smc-movement-models
Version: 1.0.0
Summary: Projet pour le cours Hidden Markov models and Sequential Monte-Carlo methods de l'ENSAE.
License: MIT
Author: Gabriel Watkinson
Author-email: gabriel.watkinson@gmail.com
Requires-Python: >3.8,<3.11
Classifier: License :: OSI Approved :: MIT License
Classifier: Programming Language :: Python :: 3
Classifier: Programming Language :: Python :: 3.9
Classifier: Programming Language :: Python :: 3.10
Requires-Dist: click (>=8.1.3,<9.0.0)
Requires-Dist: jupyter (>=1.0.0,<2.0.0)
Requires-Dist: llvmlite (==0.39.1)
Requires-Dist: matplotlib (>=3.6.2,<4.0.0)
Requires-Dist: notebook (>=6.5.2,<7.0.0)
Requires-Dist: numpy (==1.23.5)
Requires-Dist: pandas (>=1.5.2,<2.0.0)
Requires-Dist: particles (>=0.3,<0.4)
Requires-Dist: plotly (>=5.11.0,<6.0.0)
Requires-Dist: scipy (>=1.8,<1.9)
Requires-Dist: seaborn (>=0.12.1,<0.13.0)
Requires-Dist: statsmodels (>=0.13.5,<0.14.0)
Requires-Dist: tqdm (>=4.64.1,<5.0.0)
